Metadata-Version: 2.1
Name: python-golos
Version: 1.1.1
Summary: Python library for Golos blockchain
Home-page: https://github.com/bitfag/golos-python
License: MIT
Author: Vladimir Kamarzin
Author-email: vvk@vvk.pp.ru
Requires-Python: >=3.6.1,<4.0.0
Classifier: Development Status :: 5 - Production/Stable
Classifier: Intended Audience :: Developers
Classifier: License :: OSI Approved :: MIT License
Classifier: Programming Language :: Python :: 3
Classifier: Programming Language :: Python :: 3.7
Classifier: Programming Language :: Python :: 3.8
Classifier: Topic :: Software Development :: Libraries :: Python Modules
Requires-Dist: certifi (>=2020.4.5,<2021.0.0)
Requires-Dist: ecdsa (>=0.13,<0.14)
Requires-Dist: funcy (>=1.14,<2.0)
Requires-Dist: langdetect (>=1.0.8,<2.0.0)
Requires-Dist: prettytable (>=0.7.2,<0.8.0)
Requires-Dist: pycryptodome (>=3.9.7,<4.0.0)
Requires-Dist: pylibscrypt (>=1.8.0,<2.0.0)
Requires-Dist: scrypt (>=0.8.13,<0.9.0)
Requires-Dist: toolz (>=0.10.0,<0.11.0)
Requires-Dist: ujson (>=2.0.3,<3.0.0)
Requires-Dist: urllib3 (>=1.25.9,<2.0.0)
Requires-Dist: voluptuous (>=0.11.7,<0.12.0)
Requires-Dist: w3lib (>=1.21.0,<2.0.0)
Requires-Dist: websocket-client (>=0.56,<0.57)
Project-URL: Repository, https://github.com/bitfag/golos-python
